images/application-analysis.png
images/application-tier-analysis.png
images/infrastrcture-analysis-dashboard.png
images/infrastructure-services-analysis.png
images/iplists-overview.png
images/ordering-application-ruleset-overview.png
images/pce-labels-by-type.png
images/project-plan-mermaid.png
images/prompts-choose-integration.png
images/prompts-choose-prompt.png
images/prompts-finding-prompt-menu.png
images/prompts-required-parameters.png
images/ruleset-categories.png
images/security-analysis-report.png
images/security-assessment-findings-high-risk.png
images/security-assessment-findings-pci.png
images/security-assessment-findings-swift.png
images/security-remediation-plan-2.png
images/security-remediation-plan.png
images/service-role-inference.png
images/top-5-sources-and-destinations.png
images/workload-analysis.png
images/workload-traffic-identification.png
src/illumio_mcp/__init__.py
src/illumio_mcp/server.py
orange_illumio_mcp-0.1.0.dist-info/METADATA
orange_illumio_mcp-0.1.0.dist-info/WHEEL
orange_illumio_mcp-0.1.0.dist-info/entry_points.txt
orange_illumio_mcp-0.1.0.dist-info/licenses/LICENSE
orange_illumio_mcp-0.1.0.dist-info/RECORD
