Metadata-Version: 2.4
Name: orange-illumio-mcp
Version: 0.1.0
Summary: A MCP server project
Author-email: alexgoller <83632450+alexgoller@users.noreply.github.com>
License-File: LICENSE
Requires-Python: >=3.12
Requires-Dist: illumio>=1.1.3
Requires-Dist: logging>=0.4.9.6
Requires-Dist: mcp>=1.2.0
Requires-Dist: pandas>=2.2.3
Requires-Dist: python-dotenv>=1.0.1
